qibosoq/__init__.py
qibosoq/__main__.py
qibosoq/client.py
qibosoq/components/__init__.py
qibosoq/components/base.py
qibosoq/components/pulses.py
qibosoq/configuration.py
qibosoq/log.py
qibosoq/programs/__init__.py
qibosoq/programs/base.py
qibosoq/programs/flux.py
qibosoq/programs/pulse_sequence.py
qibosoq/programs/sweepers.py
qibosoq/py.typed
qibosoq/server.py
qibosoq-0.1.3.dist-info/LICENSE
qibosoq-0.1.3.dist-info/METADATA
qibosoq-0.1.3.dist-info/WHEEL
qibosoq-0.1.3.dist-info/RECORD
