Metadata-Version: 2.1
Name: qibosoq
Version: 0.1.3
Summary: QIBO Server On Qick (qibosoq) is the server component of qibolab to be run on RFSoC boards
Home-page: https://github.com/qiboteam/qibosoq/
License: Apache-2.0
Author: Rodolfo Carobene
Author-email: rodolfo.carobene@gmail.com
Requires-Python: >=3.9,<3.13
Classifier: License :: OSI Approved :: Apache Software License
Classifier: Programming Language :: Python :: 3
Classifier: Programming Language :: Python :: 3.9
Classifier: Programming Language :: Python :: 3.10
Classifier: Programming Language :: Python :: 3.11
Classifier: Programming Language :: Python :: 3.12
Classifier: Topic :: Scientific/Engineering :: Physics
Requires-Dist: numpy (>=1.26,<2.0)
Requires-Dist: qick (>=0.2.211,<=0.2.249)
Project-URL: Documentation, https://qibo.science/qibosoq/stable/
Project-URL: Repository, https://github.com/qiboteam/qibosoq/
